seeq/addons/stictionanalyser/_CreatePVOP.py
seeq/addons/stictionanalyser/_ExecutePullSignal.py
seeq/addons/stictionanalyser/_OsciFinder.py
seeq/addons/stictionanalyser/_ShapeDetection.py
seeq/addons/stictionanalyser/_SignalProcessing.py
seeq/addons/stictionanalyser/_SimilarityFinder.py
seeq/addons/stictionanalyser/__init__.py
seeq/addons/stictionanalyser/__main__.py
seeq/addons/stictionanalyser/_copy.py
seeq/addons/stictionanalyser/_funcitons_shape_detect.py
seeq/addons/stictionanalyser/_pushSignals.py
seeq/addons/stictionanalyser/_seeq_add_on.py
seeq/addons/stictionanalyser/_version.py
seeq/addons/stictionanalyser/_utils/__init__.py
seeq/addons/stictionanalyser/_utils/_common.py
seeq/addons/stictionanalyser/_utils/_permissions.py
seeq/addons/stictionanalyser/_utils/_sdl.py
seeq/addons/stictionanalyser/deployment_notebook/stiction_analyser_master.ipynb
stictionanalyser-0.0.21.dist-info/LICENSE
stictionanalyser-0.0.21.dist-info/METADATA
stictionanalyser-0.0.21.dist-info/NOTICE
stictionanalyser-0.0.21.dist-info/WHEEL
stictionanalyser-0.0.21.dist-info/top_level.txt
stictionanalyser-0.0.21.dist-info/RECORD
