Metadata-Version: 2.1
Name: stictionanalyser
Version: 0.0.21
Summary: Stiction analysis of time series data in Seeq
Home-page: https://github.com/Timothy716/seeq-stictionanalyser
Author: Timothy Essinger
Author-email: timothy.essinger@seeq.com
License: Apache License 2.0
Platform: Linux
Platform: Windows
Classifier: Programming Language :: Python :: 3.7
Classifier: Operating System :: OS Independent
Requires-Python: >=3.7
Requires-Dist: dask[complete] (>=2.18.1)
Requires-Dist: ipyvuetify (>=1.5.1)
Requires-Dist: matplotlib (>=3.1.3)
Requires-Dist: memoization (>=0.2.2)
Requires-Dist: numpy (>=1.19.5)
Requires-Dist: pandas (>=1.2.1)
Requires-Dist: plotly (>=4.5.0)
Requires-Dist: python-dateutil (>=2.8.1)
Requires-Dist: opencv-python-headless (>=4.5.4.58)
Requires-Dist: scipy (==1.6.2)
Requires-Dist: scikit-image
Requires-Dist: tzlocal (==2.0)
Requires-Dist: parver (~=0.3.1)
Requires-Dist: image (>=1.5.33)
